{
    "update_time": "2026-03-19 14:28:39",
    "lotto649": {
        "predict_numbers": [
            2,
            3,
            22,
            24,
            26,
            27
        ],
        "special_number": 31,
        "status": "Success",
        "data_count": 567
    },
    "superlotto": {
        "predict_numbers": [
            1,
            2,
            3,
            13,
            16,
            17,
            23
        ],
        "special_number": 26,
        "status": "Success",
        "data_count": 993
    }
}