{
    "update_time": "2026-04-29 00:10:23",
    "lotto649": {
        "predict_numbers": [
            6,
            10,
            14,
            25,
            26,
            32
        ],
        "special_number": 1,
        "status": "Success",
        "data_count": 83
    },
    "superlotto": {
        "predict_numbers": [
            6,
            8,
            27,
            33,
            35,
            38
        ],
        "special_number": 7,
        "status": "Success",
        "data_count": 69
    }
}