{
    "update_time": "2026-07-14 23:27:08",
    "lotto649": {
        "predict_numbers": [
            10,
            25,
            34,
            36,
            45,
            46
        ],
        "special_number": 4,
        "status": "Success",
        "data_count": 79
    },
    "superlotto": {
        "predict_numbers": [
            11,
            24,
            29,
            32,
            35,
            38
        ],
        "special_number": 7,
        "status": "Success",
        "data_count": 65
    }
}